{
 "actions": [],
 "creation": "2020-12-30 18:04:07.549175",
 "doctype": "DocType",
 "editable_grid": 1,
 "engine": "InnoDB",
 "field_order": [
  "document",
  "date_added_to_file",
  "comments"
 ],
 "fields": [
  {
   "default": "Other",
   "fieldname": "document",
   "fieldtype": "Select",
   "in_list_view": 1,
   "label": "Document",
   "options": "Staff Onboarding\nInterview Record\nReference Check Form\nResume\nCopy of Working with Children Card\nPolice check (International if applicable)\nDWES Check cleared\nCode of conduct\nPrivacy and Confidentiality Declaration\nEmployment Contract\nCopy of qualification/s and statement of results\nCopy of First Aid Certificate\nCopy of CPR Certificate\nInduction Checklist\nSupervisory Meeting Records\nPerformance Appraisals\nExit Interview\nOther"
  },
  {
   "default": "Today",
   "fieldname": "date_added_to_file",
   "fieldtype": "Date",
   "in_list_view": 1,
   "label": "Date Added to File"
  },
  {
   "fieldname": "comments",
   "fieldtype": "Data",
   "in_list_view": 1,
   "label": "Comments"
  }
 ],
 "index_web_pages_for_search": 1,
 "istable": 1,
 "links": [],
 "modified": "2021-07-04 00:56:35.700308",
 "modified_by": "Administrator",
 "module": "Staff Management",
 "name": "File Checklist",
 "owner": "Administrator",
 "permissions": [],
 "quick_entry": 1,
 "sort_field": "modified",
 "sort_order": "DESC",
 "track_changes": 1
}